pydear/__init__.py
pydear/_version.py
pydear/imgui.py
pydear/imgui.pyi
pydear/imgui_internal.py
pydear/imgui_internal.pyi
pydear/imnodes.py
pydear/imnodes.pyi
pydear/impl.pyd
pydear/nanovg.py
pydear/nanovg.pyi
pydear/py.typed
pydear/assets/Utah_teapot_(solid).stl
pydear/assets/gizmo.fs
pydear/assets/gizmo.vs
pydear/assets/mesh.fs
pydear/assets/mesh.vs
pydear/assets/nanovg.fs
pydear/assets/nanovg.vs
pydear/backends/__init__.py
pydear/backends/impl_glfw.py
pydear/backends/impl_opengl3.py
pydear/gizmo/__init__.py
pydear/gizmo/gizmo.py
pydear/gizmo/gizmo_drag_handler.py
pydear/gizmo/gizmo_select_handler.py
pydear/gizmo/gizmo_vertex_buffer.py
pydear/gizmo/primitive.py
pydear/gizmo/screen_slider.py
pydear/gizmo/shader_vertex.py
pydear/gizmo/shapes/__init__.py
pydear/gizmo/shapes/cube_shape.py
pydear/gizmo/shapes/ring_shape.py
pydear/gizmo/shapes/shape.py
pydear/glo/__init__.py
pydear/glo/drawable.py
pydear/glo/fbo.py
pydear/glo/shader.py
pydear/glo/texture.py
pydear/glo/vao.py
pydear/glo/vbo.py
pydear/glo/vertex_layout.py
pydear/math_np/__init__.py
pydear/nanovg_backends/nanovg_impl_opengl3.py
pydear/scene/camera.py
pydear/scene/cube.py
pydear/scene/teapot.py
pydear/scene/vertex_buffer.py
pydear/utils/__init__.py
pydear/utils/dockspace.py
pydear/utils/eventproperty.py
pydear/utils/fbo_view.py
pydear/utils/filedialog.py
pydear/utils/fontloader.py
pydear/utils/glfw_app.py
pydear/utils/gui_app.py
pydear/utils/loghandler.py
pydear/utils/modal.py
pydear/utils/mouse_event.py
pydear/utils/nanovg_renderer.py
pydear/utils/nerdfont.py
pydear/utils/selector.py
pydear/utils/setting.py
pydear/utils/node_editor/editor.py
pydear/utils/node_editor/graph.py
pydear/utils/node_editor/node.py
pydear-2.1.0.dist-info/METADATA
pydear-2.1.0.dist-info/WHEEL
pydear-2.1.0.dist-info/top_level.txt
pydear-2.1.0.dist-info/RECORD
