Metadata-Version: 2.1
Name: pydear
Version: 2.1.0
Summary: Dear imgui binding
Home-page: https://github.com/ousttrue/pydear
Author: ousttrue
Author-email: ousttrue@gmail.com
Project-URL: Documentation, https://ousttrue.github.io/pydear/
Project-URL: Source, https://github.com/ousttrue/pydear
Classifier: License :: OSI Approved :: MIT License
Classifier: Programming Language :: Python :: 3.10
Requires-Dist: PyGLM
Requires-Dist: glfw
